glassbox_sdk/__init__.py
glassbox_sdk/async_decorators.py
glassbox_sdk/async_interceptor.py
glassbox_sdk/auto_detect.py
glassbox_sdk/auto_wrap.py
glassbox_sdk/cli.py
glassbox_sdk/decorators.py
glassbox_sdk/environment.py
glassbox_sdk/examples.py
glassbox_sdk/http_interceptor.py
glassbox_sdk/live_metrics.py
glassbox_sdk/logger.py
glassbox_sdk/logging_config.py
glassbox_sdk/privacy.py
glassbox_sdk/proxy.py
glassbox_sdk/sandbox.py
glassbox_sdk/serverless.py
glassbox_sdk/smart_init.py
glassbox_sdk/test_mode.py
glassbox_sdk/trust.py
glassbox_sdk/ui.py
glassbox_sdk/utils.py
glassbox_sdk/websocket_client.py
glassbox_sdk-0.1.0.dist-info/METADATA
glassbox_sdk-0.1.0.dist-info/WHEEL
glassbox_sdk-0.1.0.dist-info/entry_points.txt
glassbox_sdk-0.1.0.dist-info/top_level.txt
glassbox_sdk-0.1.0.dist-info/RECORD
