Metadata-Version: 2.4
Name: glassbox-sdk
Version: 0.1.0
Summary: See Your AI Costs in Real-Time
Home-page: https://github.com/HudsonBales/glassbox
Author: Hudson Bales
Author-email: hudson@glassbox.ai
Project-URL: Bug Reports, https://github.com/HudsonBales/glassbox/issues
Project-URL: Source, https://github.com/HudsonBales/glassbox
Project-URL: Documentation, https://github.com/HudsonBales/glassbox#readme
Keywords: ai,observability,monitoring,costs,terminal,cli,openai,anthropic,gpt-4,claude
Classifier: Development Status :: 4 - Beta
Classifier: Intended Audience :: Developers
Classifier: License :: OSI Approved :: MIT License
Classifier: Operating System :: OS Independent
Classifier: Programming Language :: Python :: 3
Classifier: Programming Language :: Python :: 3.8
Classifier: Programming Language :: Python :: 3.9
Classifier: Programming Language :: Python :: 3.10
Classifier: Programming Language :: Python :: 3.11
Classifier: Topic :: Software Development :: Libraries :: Python Modules
Classifier: Topic :: Software Development :: Quality Assurance
Requires-Python: >=3.8
Requires-Dist: requests<3.0.0,>=2.31.0
Requires-Dist: websockets<13.0.0,>=12.0; python_version >= "3.8"
Provides-Extra: test
Requires-Dist: pytest<8.0.0,>=7.4.3; extra == "test"
Requires-Dist: pytest-cov<5.0.0,>=4.1.0; extra == "test"
Requires-Dist: pytest-mock<4.0.0,>=3.12.0; extra == "test"
Provides-Extra: dev
Requires-Dist: pytest<8.0.0,>=7.4.3; extra == "dev"
Requires-Dist: pytest-cov<5.0.0,>=4.1.0; extra == "dev"
Requires-Dist: pytest-mock<4.0.0,>=3.12.0; extra == "dev"
Requires-Dist: black<24.0.0,>=23.12.1; extra == "dev"
Requires-Dist: flake8<7.0.0,>=6.1.0; extra == "dev"
Requires-Dist: mypy<2.0.0,>=1.7.1; extra == "dev"
Dynamic: author
Dynamic: author-email
Dynamic: classifier
Dynamic: description
Dynamic: description-content-type
Dynamic: home-page
Dynamic: keywords
Dynamic: project-url
Dynamic: provides-extra
Dynamic: requires-dist
Dynamic: requires-python
Dynamic: summary
